{
  "commonName": "Brown Throated Fulvetta",
  "scientificName": "Fulvetta ludlowi",
  "family": "Paradoxornithidae",
  "habitat": "High-elevation montane forests; dense lower vegetation; bamboo stands; and rhododendron thickets",
  "conservationStatus": "Least Concern (LC)",
  "photographer": "Kevin",
  "location": "xxx",
  "year": "2026",
  "story": [
    "Discover the stunning Brown Throated Fulvetta (*Fulvetta ludlowi*), a member of the diverse Paradoxornithidae family. Native to High-elevation montane forests; dense lower vegetation; bamboo stands; and rhododendron thickets, this bird faces various environmental challenges. Currently classified as Least Concern (LC) on the IUCN Red List, the Brown Throated Fulvetta represents the delicate balance of its native region. Understanding its habitat requirements and distribution is key to effective conservation planning. This species contributes to the richness of avian diversity, and this poster offers an artistic glimpse into its world.",
    "Every poster is crafted to inspire curiosity about our planet's incredible biodiversity."
  ]
}